{"available_end_tick":3,"available_start_tick":0,"channels":["WORLD"],"diffs":{"diffs_by_from_tick":{"0":{"format":"JSON","from_tick":0,"id":"diff-0","msg_type":"FRAME_DIFF","rel_path":"state/diffs/from_0000000000_to_0000000001.kvp.json","to_tick":1},"1":{"format":"JSON","from_tick":1,"id":"diff-1","msg_type":"FRAME_DIFF","rel_path":"state/diffs/from_0000000001_to_0000000002.kvp.json","to_tick":2},"2":{"format":"JSON","from_tick":2,"id":"diff-2","msg_type":"FRAME_DIFF","rel_path":"state/diffs/from_0000000002_to_0000000003.kvp.json","to_tick":3}}},"integrity":{"hash_alg":"SHA-256","records_sha256":{"diff-0":"d72b07511cb5a2503c55dbe1a9c02ab3b9bb456f08019be0e6d6eea8119ad21f","diff-1":"180ea111ee90ee6bbd7561c48894e095e3010a028db823d899572278dbf57e1b","diff-2":"b308300a5d3ada21c107fce14adea89b6181433920008959e2a60a75bd284f76","snap-0":"fd693ce569debb1b5c8b81d04335dadc56c55e9d6b340d0290f2cd5a2520711a","snap-2":"5e632358b221800f7171354834b62a29761a55b02a156566b61459d0eaa789fe"}},"keyframe_ticks":[0,2],"kvp_version":"0.1","layout":{"diff_storage":"PER_TICK_FILES","diffs_dir":"state/diffs","overlays_dir":"overlays","records_root":".","snapshots_dir":"state/snapshots"},"overlays":{"X_PSYCHO_FRAME":{"format":"JSONL","notes":null,"rel_path":"overlays/psycho_frames.jsonl"},"X_UI_EVENT_BATCH":{"format":"JSONL","notes":null,"rel_path":"overlays/ui_events.jsonl"}},"render_spec":{"asset_resolution":{"missing_ref_behavior":"error","policy":"prefer_runtime_recommended"},"coord_system":{"axis":{"x_positive":"right","y_positive":"down"},"bounds":{"max_x":10.0,"max_y":5.0,"min_x":0.0,"min_y":0.0},"origin":{"x":0.0,"y":0.0},"units":"meters","units_per_tile":1.0},"draw_order":{"agents":["humans"],"items":["props"],"rooms":["floors"]},"local_sort_key":{"direction":"asc","notes":null,"quantization":"Q1E3","source":"y_then_x"},"projection":{"kind":"isometric","recommended_iso_tile_h":32,"recommended_iso_tile_w":64},"z_layer":{"meaning":"tile","notes":null,"stable_across_run":true}},"run_anchors":{"engine_name":"Sim4","engine_version":"1.0.0","run_id":"00000000-0000-4000-8000-000000000002","schema_version":"1","seed":1,"tick_rate_hz":30,"time_origin_ms":0,"world_id":"00000000-0000-4000-8000-000000000001"},"schema_version":"1","snapshots":{"0":{"format":"JSON","id":"snap-0","msg_type":"FULL_SNAPSHOT","rel_path":"state/snapshots/tick_0000000000.kvp.json","tick":0},"2":{"format":"JSON","id":"snap-2","msg_type":"FULL_SNAPSHOT","rel_path":"state/snapshots/tick_0000000002.kvp.json","tick":2}}}